[
    {
        "NAME": "TREY MARTIN",
        "Pass_Blocking_Efficiency_HITS ALLOWED": "0",
        "Pass_Blocking_Efficiency_HURRIES ALLOWED": "0",
        "Pass_Blocking_Efficiency_PASS BLOCK SNAPS": "312",
        "Pass_Blocking_Efficiency_PBE": "100.0",
        "Pass_Blocking_Efficiency_SACKS ALLOWED": "0",
        "Pass_Blocking_Efficiency_TOTAL PRESSURE ALLOWED": "0",
        "TEAM": "Rice",
        "nameFirst": "TREY",
        "nameLast": "MARTIN"
    },
    {
        "NAME": "MARIUS YOUNG",
        "Pass_Blocking_Efficiency_HITS ALLOWED": "0",
        "Pass_Blocking_Efficiency_HURRIES ALLOWED": "0",
        "Pass_Blocking_Efficiency_PASS BLOCK SNAPS": "227",
        "Pass_Blocking_Efficiency_PBE": "100.0",
        "Pass_Blocking_Efficiency_SACKS ALLOWED": "0",
        "Pass_Blocking_Efficiency_TOTAL PRESSURE ALLOWED": "0",
        "TEAM": "VARI",
        "nameFirst": "MARIUS",
        "nameLast": "YOUNG"
    },
    {
        "NAME": "FRANK RAGNOW",
        "Pass_Blocking_Efficiency_HITS ALLOWED": "0",
        "Pass_Blocking_Efficiency_HURRIES ALLOWED": "1",
        "Pass_Blocking_Efficiency_PASS BLOCK SNAPS": "190",
        "Pass_Blocking_Efficiency_PBE": "99.6",
        "Pass_Blocking_Efficiency_SACKS ALLOWED": "0",
        "Pass_Blocking_Efficiency_TOTAL PRESSURE ALLOWED": "1",
        "TEAM": "Arkansas",
        "nameFirst": "FRANK",
        "nameLast": "RAGNOW"
    },
    {
        "NAME": "BRADLEY BOZEMAN",
        "Pass_Blocking_Efficiency_HITS ALLOWED": "0",
        "Pass_Blocking_Efficiency_HURRIES ALLOWED": "3",
        "Pass_Blocking_Efficiency_PASS BLOCK SNAPS": "395",
        "Pass_Blocking_Efficiency_PBE": "99.4",
        "Pass_Blocking_Efficiency_SACKS ALLOWED": "0",
        "Pass_Blocking_Efficiency_TOTAL PRESSURE ALLOWED": "3",
        "TEAM": "Alabama",
        "nameFirst": "BRADLEY",
        "nameLast": "BOZEMAN"
    },
    {
        "NAME": "JASHON ROBERTSON",
        "Pass_Blocking_Efficiency_HITS ALLOWED": "0",
        "Pass_Blocking_Efficiency_HURRIES ALLOWED": "0",
        "Pass_Blocking_Efficiency_PASS BLOCK SNAPS": "172",
        "Pass_Blocking_Efficiency_PBE": "99.4",
        "Pass_Blocking_Efficiency_SACKS ALLOWED": "1",
        "Pass_Blocking_Efficiency_TOTAL PRESSURE ALLOWED": "1",
        "TEAM": "Tennessee",
        "nameFirst": "JASHON",
        "nameLast": "ROBERTSON"
    },
    {
        "NAME": "DEVIN FARRIOR",
        "Pass_Blocking_Efficiency_HITS ALLOWED": "2",
        "Pass_Blocking_Efficiency_HURRIES ALLOWED": "3",
        "Pass_Blocking_Efficiency_PASS BLOCK SNAPS": "466",
        "Pass_Blocking_Efficiency_PBE": "99.2",
        "Pass_Blocking_Efficiency_SACKS ALLOWED": "0",
        "Pass_Blocking_Efficiency_TOTAL PRESSURE ALLOWED": "5",
        "TEAM": "Southern Miss",
        "nameFirst": "DEVIN",
        "nameLast": "FARRIOR"
    },
    {
        "NAME": "PATRICK MORRIS",
        "Pass_Blocking_Efficiency_HITS ALLOWED": "0",
        "Pass_Blocking_Efficiency_HURRIES ALLOWED": "2",
        "Pass_Blocking_Efficiency_PASS BLOCK SNAPS": "183",
        "Pass_Blocking_Efficiency_PBE": "99.2",
        "Pass_Blocking_Efficiency_SACKS ALLOWED": "0",
        "Pass_Blocking_Efficiency_TOTAL PRESSURE ALLOWED": "2",
        "TEAM": "TCU",
        "nameFirst": "PATRICK",
        "nameLast": "MORRIS"
    },
    {
        "NAME": "EVAN BROWN",
        "Pass_Blocking_Efficiency_HITS ALLOWED": "1",
        "Pass_Blocking_Efficiency_HURRIES ALLOWED": "7",
        "Pass_Blocking_Efficiency_PASS BLOCK SNAPS": "515",
        "Pass_Blocking_Efficiency_PBE": "98.8",
        "Pass_Blocking_Efficiency_SACKS ALLOWED": "0",
        "Pass_Blocking_Efficiency_TOTAL PRESSURE ALLOWED": "8",
        "TEAM": "SMU",
        "nameFirst": "EVAN",
        "nameLast": "BROWN"
    },
    {
        "NAME": "KEONI TAYLOR",
        "Pass_Blocking_Efficiency_HITS ALLOWED": "1",
        "Pass_Blocking_Efficiency_HURRIES ALLOWED": "3",
        "Pass_Blocking_Efficiency_PASS BLOCK SNAPS": "428",
        "Pass_Blocking_Efficiency_PBE": "98.8",
        "Pass_Blocking_Efficiency_SACKS ALLOWED": "2",
        "Pass_Blocking_Efficiency_TOTAL PRESSURE ALLOWED": "6",
        "TEAM": "San Jose St",
        "nameFirst": "KEONI",
        "nameLast": "TAYLOR"
    },
    {
        "NAME": "AUSTIN DAVIS",
        "Pass_Blocking_Efficiency_HITS ALLOWED": "0",
        "Pass_Blocking_Efficiency_HURRIES ALLOWED": "9",
        "Pass_Blocking_Efficiency_PASS BLOCK SNAPS": "517",
        "Pass_Blocking_Efficiency_PBE": "98.7",
        "Pass_Blocking_Efficiency_SACKS ALLOWED": "0",
        "Pass_Blocking_Efficiency_TOTAL PRESSURE ALLOWED": "9",
        "TEAM": "Duke",
        "nameFirst": "AUSTIN",
        "nameLast": "DAVIS"
    },
    {
        "NAME": "BRAD LUNDBLADE",
        "Pass_Blocking_Efficiency_HITS ALLOWED": "0",
        "Pass_Blocking_Efficiency_HURRIES ALLOWED": "6",
        "Pass_Blocking_Efficiency_PASS BLOCK SNAPS": "436",
        "Pass_Blocking_Efficiency_PBE": "98.7",
        "Pass_Blocking_Efficiency_SACKS ALLOWED": "1",
        "Pass_Blocking_Efficiency_TOTAL PRESSURE ALLOWED": "7",
        "TEAM": "Oklahoma St",
        "nameFirst": "BRAD",
        "nameLast": "LUNDBLADE"
    },
    {
        "NAME": "ANTONYO WOODS",
        "Pass_Blocking_Efficiency_HITS ALLOWED": "4",
        "Pass_Blocking_Efficiency_HURRIES ALLOWED": "3",
        "Pass_Blocking_Efficiency_PASS BLOCK SNAPS": "402",
        "Pass_Blocking_Efficiency_PBE": "98.7",
        "Pass_Blocking_Efficiency_SACKS ALLOWED": "0",
        "Pass_Blocking_Efficiency_TOTAL PRESSURE ALLOWED": "7",
        "TEAM": "Florida Atlantic",
        "nameFirst": "ANTONYO",
        "nameLast": "WOODS"
    },
    {
        "NAME": "DAVID NIEHAUS",
        "Pass_Blocking_Efficiency_HITS ALLOWED": "2",
        "Pass_Blocking_Efficiency_HURRIES ALLOWED": "7",
        "Pass_Blocking_Efficiency_PASS BLOCK SNAPS": "472",
        "Pass_Blocking_Efficiency_PBE": "98.6",
        "Pass_Blocking_Efficiency_SACKS ALLOWED": "0",
        "Pass_Blocking_Efficiency_TOTAL PRESSURE ALLOWED": "9",
        "TEAM": "Cincinnati",
        "nameFirst": "DAVID",
        "nameLast": "NIEHAUS"
    },
    {
        "NAME": "AUSTIN PRATT",
        "Pass_Blocking_Efficiency_HITS ALLOWED": "2",
        "Pass_Blocking_Efficiency_HURRIES ALLOWED": "1",
        "Pass_Blocking_Efficiency_PASS BLOCK SNAPS": "370",
        "Pass_Blocking_Efficiency_PBE": "98.6",
        "Pass_Blocking_Efficiency_SACKS ALLOWED": "3",
        "Pass_Blocking_Efficiency_TOTAL PRESSURE ALLOWED": "6",
        "TEAM": "UTSA",
        "nameFirst": "AUSTIN",
        "nameLast": "PRATT"
    },
    {
        "NAME": "BRIAN ALLEN",
        "Pass_Blocking_Efficiency_HITS ALLOWED": "2",
        "Pass_Blocking_Efficiency_HURRIES ALLOWED": "8",
        "Pass_Blocking_Efficiency_PASS BLOCK SNAPS": "487",
        "Pass_Blocking_Efficiency_PBE": "98.5",
        "Pass_Blocking_Efficiency_SACKS ALLOWED": "0",
        "Pass_Blocking_Efficiency_TOTAL PRESSURE ALLOWED": "10",
        "TEAM": "Michigan St",
        "nameFirst": "BRIAN",
        "nameLast": "ALLEN"
    },
    {
        "NAME": "AARON MITCHELL",
        "Pass_Blocking_Efficiency_HITS ALLOWED": "2",
        "Pass_Blocking_Efficiency_HURRIES ALLOWED": "7",
        "Pass_Blocking_Efficiency_PASS BLOCK SNAPS": "483",
        "Pass_Blocking_Efficiency_PBE": "98.4",
        "Pass_Blocking_Efficiency_SACKS ALLOWED": "1",
        "Pass_Blocking_Efficiency_TOTAL PRESSURE ALLOWED": "10",
        "TEAM": "Fresno St",
        "nameFirst": "AARON",
        "nameLast": "MITCHELL"
    },
    {
        "NAME": "COLEMAN SHELTON",
        "Pass_Blocking_Efficiency_HITS ALLOWED": "1",
        "Pass_Blocking_Efficiency_HURRIES ALLOWED": "7",
        "Pass_Blocking_Efficiency_PASS BLOCK SNAPS": "388",
        "Pass_Blocking_Efficiency_PBE": "98.2",
        "Pass_Blocking_Efficiency_SACKS ALLOWED": "1",
        "Pass_Blocking_Efficiency_TOTAL PRESSURE ALLOWED": "9",
        "TEAM": "Washington",
        "nameFirst": "COLEMAN",
        "nameLast": "SHELTON"
    },
    {
        "NAME": "WILL CLAPP",
        "Pass_Blocking_Efficiency_HITS ALLOWED": "0",
        "Pass_Blocking_Efficiency_HURRIES ALLOWED": "7",
        "Pass_Blocking_Efficiency_PASS BLOCK SNAPS": "353",
        "Pass_Blocking_Efficiency_PBE": "98.2",
        "Pass_Blocking_Efficiency_SACKS ALLOWED": "1",
        "Pass_Blocking_Efficiency_TOTAL PRESSURE ALLOWED": "8",
        "TEAM": "LSU",
        "nameFirst": "WILL",
        "nameLast": "CLAPP"
    },
    {
        "NAME": "TIM MCAULIFFE",
        "Pass_Blocking_Efficiency_HITS ALLOWED": "1",
        "Pass_Blocking_Efficiency_HURRIES ALLOWED": "vv7",
        "Pass_Blocking_Efficiency_PASS BLOCK SNAPS": "374",
        "Pass_Blocking_Efficiency_PBE": "98.1",
        "Pass_Blocking_Efficiency_SACKS ALLOWED": "1",
        "Pass_Blocking_Efficiency_TOTAL PRESSURE ALLOWED": "9",
        "TEAM": "Bowling Green",
        "nameFirst": "TIM",
        "nameLast": "MCAULIFFE"
    },
    {
        "NAME": "TEJAN KOROMA",
        "Pass_Blocking_Efficiency_HITS ALLOWED": "4",
        "Pass_Blocking_Efficiency_HURRIES ALLOWED": "7",
        "Pass_Blocking_Efficiency_PASS BLOCK SNAPS": "459",
        "Pass_Blocking_Efficiency_PBE": "98.0",
        "Pass_Blocking_Efficiency_SACKS ALLOWED": "1",
        "Pass_Blocking_Efficiency_TOTAL PRESSURE ALLOWED": "12",
        "TEAM": "BYU",
        "nameFirst": "TEJAN",
        "nameLast": "KOROMA"
    },
    {
        "NAME": "NATHAN PUTHOFF",
        "Pass_Blocking_Efficiency_HITS ALLOWED": "1",
        "Pass_Blocking_Efficiency_HURRIES ALLOWED": "7",
        "Pass_Blocking_Efficiency_PASS BLOCK SNAPS": "300",
        "Pass_Blocking_Efficiency_PBE": "98.0",
        "Pass_Blocking_Efficiency_SACKS ALLOWED": "0",
        "Pass_Blocking_Efficiency_TOTAL PRESSURE ALLOWED": "8",
        "TEAM": "Kent St",
        "nameFirst": "NATHAN",
        "nameLast": "PUTHOFF"
    },
    {
        "NAME": "SCOTT QUESSENBERRY",
        "Pass_Blocking_Efficiency_HITS ALLOWED": "4",
        "Pass_Blocking_Efficiency_HURRIES ALLOWED": "10",
        "Pass_Blocking_Efficiency_PASS BLOCK SNAPS": "581",
        "Pass_Blocking_Efficiency_PBE": "97.8",
        "Pass_Blocking_Efficiency_SACKS ALLOWED": "2",
        "Pass_Blocking_Efficiency_TOTAL PRESSURE ALLOWED": "16",
        "TEAM": "UCLA",
        "nameFirst": "SCOTT",
        "nameLast": "QUESSENBERRY"
    },
    {
        "NAME": "MASON HAMPTON",
        "Pass_Blocking_Efficiency_HITS ALLOWED": "4",
        "Pass_Blocking_Efficiency_HURRIES ALLOWED": "9",
        "Pass_Blocking_Efficiency_PASS BLOCK SNAPS": "491",
        "Pass_Blocking_Efficiency_PBE": "97.8",
        "Pass_Blocking_Efficiency_SACKS ALLOWED": "1",
        "Pass_Blocking_Efficiency_TOTAL PRESSURE ALLOWED": "14",
        "TEAM": "Boise St",
        "nameFirst": "MASON",
        "nameLast": "HAMPTON"
    },
    {
        "NAME": "J.P. QUINN",
        "Pass_Blocking_Efficiency_HITS ALLOWED": "4",
        "Pass_Blocking_Efficiency_HURRIES ALLOWED": "7",
        "Pass_Blocking_Efficiency_PASS BLOCK SNAPS": "377",
        "Pass_Blocking_Efficiency_PBE": "97.8",
        "Pass_Blocking_Efficiency_SACKS ALLOWED": "0",
        "Pass_Blocking_Efficiency_TOTAL PRESSURE ALLOWED": "11",
        "TEAM": "Central Michigan",
        "nameFirst": "J.P.",
        "nameLast": "QUINN"
    },
    {
        "NAME": "JAMES DANIELS",
        "Pass_Blocking_Efficiency_HITS ALLOWED": "1",
        "Pass_Blocking_Efficiency_HURRIES ALLOWED": "6",
        "Pass_Blocking_Efficiency_PASS BLOCK SNAPS": "371",
        "Pass_Blocking_Efficiency_PBE": "97.8",
        "Pass_Blocking_Efficiency_SACKS ALLOWED": "3",
        "Pass_Blocking_Efficiency_TOTAL PRESSURE ALLOWED": "10",
        "TEAM": "Iowa",
        "nameFirst": "JAMES",
        "nameLast": "DANIELS"
    },
    {
        "NAME": "STEPHEN ERICKSEN",
        "Pass_Blocking_Efficiency_HITS ALLOWED": "0",
        "Pass_Blocking_Efficiency_HURRIES ALLOWED": "6",
        "Pass_Blocking_Efficiency_PASS BLOCK SNAPS": "293",
        "Pass_Blocking_Efficiency_PBE": "97.8",
        "Pass_Blocking_Efficiency_SACKS ALLOWED": "2",
        "Pass_Blocking_Efficiency_TOTAL PRESSURE ALLOWED": "8",
        "TEAM": "Akron",
        "nameFirst": "STEPHEN",
        "nameLast": "ERICKSEN"
    },
    {
        "NAME": "JAKE PRUEHS",
        "Pass_Blocking_Efficiency_HITS ALLOWED": "2",
        "Pass_Blocking_Efficiency_HURRIES ALLOWED": "9",
        "Pass_Blocking_Efficiency_PASS BLOCK SNAPS": "357",
        "Pass_Blocking_Efficiency_PBE": "97.7",
        "Pass_Blocking_Efficiency_SACKS ALLOWED": "0",
        "Pass_Blocking_Efficiency_TOTAL PRESSURE ALLOWED": "11",
        "TEAM": "Ohio",
        "nameFirst": "JAKE",
        "nameLast": "PRUEHS"
    },
    {
        "NAME": "ERIC GALLO",
        "Pass_Blocking_Efficiency_HITS ALLOWED": "2",
        "Pass_Blocking_Efficiency_HURRIES ALLOWED": "11",
        "Pass_Blocking_Efficiency_PASS BLOCK SNAPS": "441",
        "Pass_Blocking_Efficiency_PBE": "97.6",
        "Pass_Blocking_Efficiency_SACKS ALLOWED": "1",
        "Pass_Blocking_Efficiency_TOTAL PRESSURE ALLOWED": "14",
        "TEAM": "Virginia Tech",
        "nameFirst": "ERIC",
        "nameLast": "GALLO"
    },
    {
        "NAME": "BILLY PRICE",
        "Pass_Blocking_Efficiency_HITS ALLOWED": "1",
        "Pass_Blocking_Efficiency_HURRIES ALLOWED": "10",
        "Pass_Blocking_Efficiency_PASS BLOCK SNAPS": "433",
        "Pass_Blocking_Efficiency_PBE": "97.6",
        "Pass_Blocking_Efficiency_SACKS ALLOWED": "2",
        "Pass_Blocking_Efficiency_TOTAL PRESSURE ALLOWED": "13",
        "TEAM": "Ohio St",
        "nameFirst": "BILLY",
        "nameLast": "PRICE"
    },
    {
        "NAME": "COLEMAN THOMAS",
        "Pass_Blocking_Efficiency_HITS ALLOWED": "1",
        "Pass_Blocking_Efficiency_HURRIES ALLOWED": "4",
        "Pass_Blocking_Efficiency_PASS BLOCK SNAPS": "154",
        "Pass_Blocking_Efficiency_PBE": "97.6",
        "Pass_Blocking_Efficiency_SACKS ALLOWED": "0",
        "Pass_Blocking_Efficiency_TOTAL PRESSURE ALLOWED": "5",
        "TEAM": "Tennessee",
        "nameFirst": "COLEMAN",
        "nameLast": "THOMAS"
    },
    {
        "NAME": "ALAN KNOTT",
        "Pass_Blocking_Efficiency_HITS ALLOWED": "2",
        "Pass_Blocking_Efficiency_HURRIES ALLOWED": "12",
        "Pass_Blocking_Efficiency_PASS BLOCK SNAPS": "457",
        "Pass_Blocking_Efficiency_PBE": "97.5",
        "Pass_Blocking_Efficiency_SACKS ALLOWED": "1",
        "Pass_Blocking_Efficiency_TOTAL PRESSURE ALLOWED": "15",
        "TEAM": "South Carolina",
        "nameFirst": "ALAN",
        "nameLast": "KNOTT"
    },
    {
        "NAME": "NICO FALAH",
        "Pass_Blocking_Efficiency_HITS ALLOWED": "3",
        "Pass_Blocking_Efficiency_HURRIES ALLOWED": "13",
        "Pass_Blocking_Efficiency_PASS BLOCK SNAPS": "546",
        "Pass_Blocking_Efficiency_PBE": "97.4",
        "Pass_Blocking_Efficiency_SACKS ALLOWED": "2",
        "Pass_Blocking_Efficiency_TOTAL PRESSURE ALLOWED": "18",
        "TEAM": "USC",
        "nameFirst": "NICO",
        "nameLast": "FALAH"
    },
    {
        "NAME": "JAKE BENNETT",
        "Pass_Blocking_Efficiency_HITS ALLOWED": "7",
        "Pass_Blocking_Efficiency_HURRIES ALLOWED": "6",
        "Pass_Blocking_Efficiency_PASS BLOCK SNAPS": "483",
        "Pass_Blocking_Efficiency_PBE": "97.4",
        "Pass_Blocking_Efficiency_SACKS ALLOWED": "3",
        "Pass_Blocking_Efficiency_TOTAL PRESSURE ALLOWED": "16",
        "TEAM": "Colorado St",
        "nameFirst": "JAKE",
        "nameLast": "BENNETT"
    },
    {
        "NAME": "AUSTIN SCHLOTTMANN",
        "Pass_Blocking_Efficiency_HITS ALLOWED": "2",
        "Pass_Blocking_Efficiency_HURRIES ALLOWED": "9",
        "Pass_Blocking_Efficiency_PASS BLOCK SNAPS": "351",
        "Pass_Blocking_Efficiency_PBE": "97.4",
        "Pass_Blocking_Efficiency_SACKS ALLOWED": "1",
        "Pass_Blocking_Efficiency_TOTAL PRESSURE ALLOWED": "12",
        "TEAM": "TCU",
        "nameFirst": "AUSTIN",
        "nameLast": "SCHLOTTMANN"
    },
    {
        "NAME": "BLAISE FOUNTAIN",
        "Pass_Blocking_Efficiency_HITS ALLOWED": "3",
        "Pass_Blocking_Efficiency_HURRIES ALLOWED": "7",
        "Pass_Blocking_Efficiency_PASS BLOCK SNAPS": "287",
        "Pass_Blocking_Efficiency_PBE": "97.4",
        "Pass_Blocking_Efficiency_SACKS ALLOWED": "0",
        "Pass_Blocking_Efficiency_TOTAL PRESSURE ALLOWED": "10",
        "TEAM": "New Mexico",
        "nameFirst": "BLAISE",
        "nameLast": "FOUNTAIN"
    },
    {
        "NAME": "JAMIN SMITH",
        "Pass_Blocking_Efficiency_HITS ALLOWED": "4",
        "Pass_Blocking_Efficiency_HURRIES ALLOWED": "17",
        "Pass_Blocking_Efficiency_PASS BLOCK SNAPS": "586",
        "Pass_Blocking_Efficiency_PBE": "97.3",
        "Pass_Blocking_Efficiency_SACKS ALLOWED": "0",
        "Pass_Blocking_Efficiency_TOTAL PRESSURE ALLOWED": "21",
        "TEAM": "New Mexico St",
        "nameFirst": "JAMIN",
        "nameLast": "SMITH"
    },
    {
        "NAME": "CAM DILLARD",
        "Pass_Blocking_Efficiency_HITS ALLOWED": "2",
        "Pass_Blocking_Efficiency_HURRIES ALLOWED": "10",
        "Pass_Blocking_Efficiency_PASS BLOCK SNAPS": "381",
        "Pass_Blocking_Efficiency_PBE": "97.1",
        "Pass_Blocking_Efficiency_SACKS ALLOWED": "2",
        "Pass_Blocking_Efficiency_TOTAL PRESSURE ALLOWED": "14",
        "TEAM": "North Carolina",
        "nameFirst": "CAM",
        "nameLast": "DILLARD"
    },
    {
        "NAME": "BRENDAN VECHERY",
        "Pass_Blocking_Efficiency_HITS ALLOWED": "6",
        "Pass_Blocking_Efficiency_HURRIES ALLOWED": "6",
        "Pass_Blocking_Efficiency_PASS BLOCK SNAPS": "341",
        "Pass_Blocking_Efficiency_PBE": "97.1",
        "Pass_Blocking_Efficiency_SACKS ALLOWED": "1",
        "Pass_Blocking_Efficiency_TOTAL PRESSURE ALLOWED": "13",
        "TEAM": "Connecticut",
        "nameFirst": "BRENDAN",
        "nameLast": "VECHERY"
    },
    {
        "NAME": "CAMERON RUFF",
        "Pass_Blocking_Efficiency_HITS ALLOWED": "3",
        "Pass_Blocking_Efficiency_HURRIES ALLOWED": "12",
        "Pass_Blocking_Efficiency_PASS BLOCK SNAPS": "363",
        "Pass_Blocking_Efficiency_PBE": "96.9",
        "Pass_Blocking_Efficiency_SACKS ALLOWED": "0",
        "Pass_Blocking_Efficiency_TOTAL PRESSURE ALLOWED": "15",
        "TEAM": "USF",
        "nameFirst": "CAMERON",
        "nameLast": "RUFF"
    },
    {
        "NAME": "ERICK WREN",
        "Pass_Blocking_Efficiency_HITS ALLOWED": "1",
        "Pass_Blocking_Efficiency_HURRIES ALLOWED": "13",
        "Pass_Blocking_Efficiency_PASS BLOCK SNAPS": "483",
        "Pass_Blocking_Efficiency_PBE": "96.8",
        "Pass_Blocking_Efficiency_SACKS ALLOWED": "5",
        "Pass_Blocking_Efficiency_TOTAL PRESSURE ALLOWED": "19",
        "TEAM": "Oklahoma",
        "nameFirst": "ERICK",
        "nameLast": "WREN"
    },
    {
        "NAME": "AUSTIN DOAN",
        "Pass_Blocking_Efficiency_HITS ALLOWED": "2",
        "Pass_Blocking_Efficiency_HURRIES ALLOWED": "3",
        "Pass_Blocking_Efficiency_PASS BLOCK SNAPS": "150",
        "Pass_Blocking_Efficiency_PBE": "96.8",
        "Pass_Blocking_Efficiency_SACKS ALLOWED": "1",
        "Pass_Blocking_Efficiency_TOTAL PRESSURE ALLOWED": "6",
        "TEAM": "Central Michigan",
        "nameFirst": "AUSTIN",
        "nameLast": "DOAN"
    },
    {
        "NAME": "A.J. MCCOLLUM",
        "Pass_Blocking_Efficiency_HITS ALLOWED": "7",
        "Pass_Blocking_Efficiency_HURRIES ALLOWED": "10",
        "Pass_Blocking_Efficiency_PASS BLOCK SNAPS": "505",
        "Pass_Blocking_Efficiency_PBE": "96.7",
        "Pass_Blocking_Efficiency_SACKS ALLOWED": "4",
        "Pass_Blocking_Efficiency_TOTAL PRESSURE ALLOWED": "21",
        "TEAM": "Arizona St",
        "nameFirst": "A.J.",
        "nameLast": "MCCOLLUM"
    },
    {
        "NAME": "JONATHAN HUCKINS",
        "Pass_Blocking_Efficiency_HITS ALLOWED": "3",
        "Pass_Blocking_Efficiency_HURRIES ALLOWED": "8",
        "Pass_Blocking_Efficiency_PASS BLOCK SNAPS": "309",
        "Pass_Blocking_Efficiency_PBE": "96.7",
        "Pass_Blocking_Efficiency_SACKS ALLOWED": "2",
        "Pass_Blocking_Efficiency_TOTAL PRESSURE ALLOWED": "13",
        "TEAM": "Colorado",
        "nameFirst": "JONATHAN",
        "nameLast": "HUCKINS"
    },
    {
        "NAME": "DOMINIC ESPOSITO",
        "Pass_Blocking_Efficiency_HITS ALLOWED": "1",
        "Pass_Blocking_Efficiency_HURRIES ALLOWED": "15",
        "Pass_Blocking_Efficiency_PASS BLOCK SNAPS": "443",
        "Pass_Blocking_Efficiency_PBE": "96.6",
        "Pass_Blocking_Efficiency_SACKS ALLOWED": "3",
        "Pass_Blocking_Efficiency_TOTAL PRESSURE ALLOWED": "19",
        "TEAM": "South Alabama",
        "nameFirst": "DOMINIC",
        "nameLast": "ESPOSITO"
    },
    {
        "NAME": "CASEY DUNN",
        "Pass_Blocking_Efficiency_HITS ALLOWED": "0",
        "Pass_Blocking_Efficiency_HURRIES ALLOWED": "13",
        "Pass_Blocking_Efficiency_PASS BLOCK SNAPS": "320",
        "Pass_Blocking_Efficiency_PBE": "96.6",
        "Pass_Blocking_Efficiency_SACKS ALLOWED": "1",
        "Pass_Blocking_Efficiency_TOTAL PRESSURE ALLOWED": "14",
        "TEAM": "Auburn",
        "nameFirst": "CASEY",
        "nameLast": "DUNN"
    },
    {
        "NAME": "BRAD NORTH",
        "Pass_Blocking_Efficiency_HITS ALLOWED": "3",
        "Pass_Blocking_Efficiency_HURRIES ALLOWED": "14",
        "Pass_Blocking_Efficiency_PASS BLOCK SNAPS": "510",
        "Pass_Blocking_Efficiency_PBE": "96.5",
        "Pass_Blocking_Efficiency_SACKS ALLOWED": "5",
        "Pass_Blocking_Efficiency_TOTAL PRESSURE ALLOWED": "22",
        "TEAM": "Northwestern",
        "nameFirst": "BRAD",
        "nameLast": "NORTH"
    },
    {
        "NAME": "ALEX NORTON",
        "Pass_Blocking_Efficiency_HITS ALLOWED": "2",
        "Pass_Blocking_Efficiency_HURRIES ALLOWED": "4",
        "Pass_Blocking_Efficiency_PASS BLOCK SNAPS": "155",
        "Pass_Blocking_Efficiency_PBE": "96.5",
        "Pass_Blocking_Efficiency_SACKS ALLOWED": "1",
        "Pass_Blocking_Efficiency_TOTAL PRESSURE ALLOWED": "7",
        "TEAM": "Air Force",
        "nameFirst": "ALEX",
        "nameLast": "NORTON"
    },
    {
        "NAME": "PATRICK KUGLER",
        "Pass_Blocking_Efficiency_HITS ALLOWED": "3",
        "Pass_Blocking_Efficiency_HURRIES ALLOWED": "12",
        "Pass_Blocking_Efficiency_PASS BLOCK SNAPS": "371",
        "Pass_Blocking_Efficiency_PBE": "96.4",
        "Pass_Blocking_Efficiency_SACKS ALLOWED": "2",
        "Pass_Blocking_Efficiency_TOTAL PRESSURE ALLOWED": "17",
        "TEAM": "Michigan",
        "nameFirst": "PATRICK",
        "nameLast": "KUGLER"
    },
    {
        "NAME": "NATE JEPPESEN",
        "Pass_Blocking_Efficiency_HITS ALLOWED": "0",
        "Pass_Blocking_Efficiency_HURRIES ALLOWED": "10",
        "Pass_Blocking_Efficiency_PASS BLOCK SNAPS": "315",
        "Pass_Blocking_Efficiency_PBE": "96.0",
        "Pass_Blocking_Efficiency_SACKS ALLOWED": "5",
        "Pass_Blocking_Efficiency_TOTAL PRESSURE ALLOWED": "15",
        "TEAM": "Toledo",
        "nameFirst": "NATE",
        "nameLast": "JEPPESEN"
    },
    {
        "NAME": "J'ONDRAY SANDERS",
        "Pass_Blocking_Efficiency_HITS ALLOWED": "2",
        "Pass_Blocking_Efficiency_HURRIES ALLOWED": "12",
        "Pass_Blocking_Efficiency_PASS BLOCK SNAPS": "303",
        "Pass_Blocking_Efficiency_PBE": "95.9",
        "Pass_Blocking_Efficiency_SACKS ALLOWED": "2",
        "Pass_Blocking_Efficiency_TOTAL PRESSURE ALLOWED": "16",
        "TEAM": "UNLV",
        "nameFirst": "J'ONDRAY",
        "nameLast": "SANDERS"
    }
]